{"namespace":"EvoNotesDesignSystem_aff30d","components":[{"name":"Avatar","sourcePath":"components/core/Avatar.jsx"},{"name":"Badge","sourcePath":"components/core/Badge.jsx"},{"name":"Button","sourcePath":"components/core/Button.jsx"},{"name":"Card","sourcePath":"components/core/Card.jsx"},{"name":"Checkbox","sourcePath":"components/core/Checkbox.jsx"},{"name":"Icon","sourcePath":"components/core/Icon.jsx"},{"name":"IconButton","sourcePath":"components/core/IconButton.jsx"},{"name":"Input","sourcePath":"components/core/Input.jsx"},{"name":"NoteCard","sourcePath":"components/core/NoteCard.jsx"},{"name":"ProgressBar","sourcePath":"components/core/ProgressBar.jsx"},{"name":"SegmentedControl","sourcePath":"components/core/SegmentedControl.jsx"},{"name":"Switch","sourcePath":"components/core/Switch.jsx"},{"name":"Tabs","sourcePath":"components/core/Tabs.jsx"},{"name":"DashboardScreen","sourcePath":"ui_kits/web-app/DashboardScreen.jsx"},{"name":"FlashcardsScreen","sourcePath":"ui_kits/web-app/FlashcardsScreen.jsx"},{"name":"QuizScreen","sourcePath":"ui_kits/web-app/QuizScreen.jsx"},{"name":"ScheduleScreen","sourcePath":"ui_kits/web-app/ScheduleScreen.jsx"},{"name":"Sidebar","sourcePath":"ui_kits/web-app/Sidebar.jsx"},{"name":"WorkspaceOpenScreen","sourcePath":"ui_kits/web-app/WorkspaceOpenScreen.jsx"},{"name":"WorkspacesScreen","sourcePath":"ui_kits/web-app/WorkspacesScreen.jsx"}],"startingPoints":[],"cards":[{"path":"guidelines/brand-logo.card.html","group":"Brand","viewport":"700x180","subtitle":"Monogram mark + horizontal lockup","name":"Logo"},{"path":"guidelines/colors-neutrals.card.html","group":"Colors","viewport":"700x150","subtitle":"Surfaces & ink scale","name":"Core neutrals"},{"path":"guidelines/colors-notes.card.html","group":"Colors","viewport":"700x172","subtitle":"Sticky-note fills + the Course/Workspace tag tints","name":"Note & type-tag fills"},{"path":"guidelines/colors-primary.card.html","group":"Colors","viewport":"700x150","subtitle":"Near-black actions + brand purple","name":"Primary & purple accent"},{"path":"guidelines/colors-semantic.card.html","group":"Colors","viewport":"700x172","subtitle":"Success · info · warning · error, each with a soft tint","name":"Semantic colors"},{"path":"components/core/buttons.card.html","group":"Components","viewport":"700x340","subtitle":"Button, IconButton, SegmentedControl, Tabs","name":"Buttons & actions"},{"path":"components/core/data-display.card.html","group":"Components","viewport":"700x360","subtitle":"Card, NoteCard, Badge, Avatar, ProgressBar, Input, Checkbox, Switch","name":"Data display & forms"},{"path":"guidelines/spacing-radii.card.html","group":"Spacing","viewport":"700x150","subtitle":"XL rounding is the house style","name":"Corner radii"},{"path":"guidelines/spacing-scale.card.html","group":"Spacing","viewport":"700x150","subtitle":"4px base — generous by default","name":"Spacing scale"},{"path":"guidelines/spacing-shadows.card.html","group":"Spacing","viewport":"700x172","subtitle":"Soft, low-contrast lifts","name":"Elevation / shadows"},{"path":"guidelines/type-body.card.html","group":"Type","viewport":"700x210","subtitle":"The everyday reading sizes","name":"Body, meta & label"},{"path":"guidelines/type-headings.card.html","group":"Type","viewport":"700x220","subtitle":"Plus Jakarta Sans, tight tracking","name":"Display & headings"},{"path":"guidelines/type-weights.card.html","group":"Type","viewport":"700x150","subtitle":"Fustat — the single brand typeface","name":"Weights"},{"path":"ui_kits/web-app/index.html","group":"Web App","viewport":"1200x780","subtitle":"Interactive study app — dashboard, workspaces, NotebookLM workspace, practice, schedule","name":"Evo Notes web app"}],"templates":[],"globalCssPaths":["tokens/fonts.css","tokens/colors.css","tokens/typography.css","tokens/spacing.css","tokens/base.css","styles.css"],"tokens":[{"name":"--ev-white","value":"#ffffff","kind":"color","definedIn":"tokens/colors.css"},{"name":"--ev-surface","value":"#ffffff","kind":"color","definedIn":"tokens/colors.css"},{"name":"--ev-surface-2","value":"#fcfcfc","kind":"color","definedIn":"tokens/colors.css"},{"name":"--ev-bg","value":"#f1f3f2","kind":"color","definedIn":"tokens/colors.css"},{"name":"--ev-bg-soft","value":"#f7f8f8","kind":"color","definedIn":"tokens/colors.css"},{"name":"--ev-bg-deep","value":"#e0e5e2","kind":"color","definedIn":"tokens/colors.css"},{"name":"--ev-bg-page","value":"#f4f6f5","kind":"color","definedIn":"tokens/colors.css"},{"name":"--ev-bg-sage","value":"#e6e9ea","kind":"color","definedIn":"tokens/colors.css"},{"name":"--ev-ink","value":"#222222","kind":"color","definedIn":"tokens/colors.css"},{"name":"--ev-ink-soft","value":"#6b6b6b","kind":"color","definedIn":"tokens/colors.css"},{"name":"--ev-ink-faint","value":"#9a9a9a","kind":"color","definedIn":"tokens/colors.css"},{"name":"--ev-ink-ghost","value":"#bcbcbc","kind":"color","definedIn":"tokens/colors.css"},{"name":"--ev-line","value":"#ececec","kind":"color","definedIn":"tokens/colors.css"},{"name":"--ev-border","value":"#e6e6e6","kind":"color","definedIn":"tokens/colors.css"},{"name":"--ev-border-strong","value":"#d8d8d8","kind":"color","definedIn":"tokens/colors.css"},{"name":"--ev-primary","value":"#222222","kind":"color","definedIn":"tokens/colors.css"},{"name":"--ev-primary-hover","value":"#000000","kind":"color","definedIn":"tokens/colors.css"},{"name":"--ev-primary-content","value":"#ffffff","kind":"color","definedIn":"tokens/colors.css"},{"name":"--ev-purple","value":"#8c7bd9","kind":"color","definedIn":"tokens/colors.css"},{"name":"--ev-purple-hover","value":"#7866cf","kind":"color","definedIn":"tokens/colors.css"},{"name":"--ev-purple-content","value":"#ffffff","kind":"color","definedIn":"tokens/colors.css"},{"name":"--ev-purple-soft","value":"#ece6f6","kind":"color","definedIn":"tokens/colors.css"},{"name":"--ev-purple-softer","value":"#f3eefb","kind":"color","definedIn":"tokens/colors.css"},{"name":"--ev-purple-ink","value":"#5b4aa8","kind":"color","definedIn":"tokens/colors.css"},{"name":"--ev-success","value":"#7bd9ab","kind":"color","definedIn":"tokens/colors.css"},{"name":"--ev-success-ink","value":"#2f7d56","kind":"color","definedIn":"tokens/colors.css"},{"name":"--ev-success-soft","value":"#e7f6ee","kind":"color","definedIn":"tokens/colors.css"},{"name":"--ev-green-note","value":"#aef07f","kind":"color","definedIn":"tokens/colors.css"},{"name":"--ev-green-note-ink","value":"#2f4a1f","kind":"color","definedIn":"tokens/colors.css"},{"name":"--ev-green-soft","value":"#eaf3e6","kind":"color","definedIn":"tokens/colors.css"},{"name":"--ev-green-ink","value":"#3c5230","kind":"color","definedIn":"tokens/colors.css"},{"name":"--ev-info","value":"#8ec9f9","kind":"color","definedIn":"tokens/colors.css"},{"name":"--ev-info-ink","value":"#2e6bb0","kind":"color","definedIn":"tokens/colors.css"},{"name":"--ev-info-soft","value":"#e4ecf8","kind":"color","definedIn":"tokens/colors.css"},{"name":"--ev-warning","value":"#ffcc61","kind":"color","definedIn":"tokens/colors.css"},{"name":"--ev-warning-ink","value":"#a9772a","kind":"color","definedIn":"tokens/colors.css"},{"name":"--ev-warning-soft","value":"#f6ecdc","kind":"color","definedIn":"tokens/colors.css"},{"name":"--ev-error","value":"#f98e9e","kind":"color","definedIn":"tokens/colors.css"},{"name":"--ev-error-ink","value":"#b8475a","kind":"color","definedIn":"tokens/colors.css"},{"name":"--ev-error-soft","value":"#fde7ea","kind":"color","definedIn":"tokens/colors.css"},{"name":"--text-strong","value":"var(--ev-ink)","kind":"font","definedIn":"tokens/colors.css"},{"name":"--text-body","value":"var(--ev-ink-soft)","kind":"font","definedIn":"tokens/colors.css"},{"name":"--text-muted","value":"var(--ev-ink-faint)","kind":"font","definedIn":"tokens/colors.css"},{"name":"--text-placeholder","value":"var(--ev-ink-ghost)","kind":"font","definedIn":"tokens/colors.css"},{"name":"--surface-page","value":"var(--ev-bg)","kind":"color","definedIn":"tokens/colors.css"},{"name":"--surface-card","value":"var(--ev-surface)","kind":"color","definedIn":"tokens/colors.css"},{"name":"--surface-rail","value":"var(--ev-surface-2)","kind":"color","definedIn":"tokens/colors.css"},{"name":"--border-card","value":"var(--ev-border)","kind":"color","definedIn":"tokens/colors.css"},{"name":"--border-divider","value":"var(--ev-line)","kind":"color","definedIn":"tokens/colors.css"},{"name":"--action-primary-bg","value":"var(--ev-primary)","kind":"color","definedIn":"tokens/colors.css"},{"name":"--action-primary-fg","value":"var(--ev-primary-content)","kind":"color","definedIn":"tokens/colors.css"},{"name":"--action-accent-bg","value":"var(--ev-purple)","kind":"color","definedIn":"tokens/colors.css"},{"name":"--action-accent-fg","value":"var(--ev-purple-content)","kind":"color","definedIn":"tokens/colors.css"},{"name":"--ev-font-sans","value":"'Fustat', system-ui, -apple-system, 'Segoe UI', sans-serif","kind":"font","definedIn":"tokens/typography.css"},{"name":"--ev-font-hand","value":"var(--ev-font-sans)","kind":"font","definedIn":"tokens/typography.css"},{"name":"--ev-w-regular","value":"400","kind":"other","definedIn":"tokens/typography.css","annotation":"other"},{"name":"--ev-w-medium","value":"500","kind":"other","definedIn":"tokens/typography.css","annotation":"other"},{"name":"--ev-w-semibold","value":"600","kind":"other","definedIn":"tokens/typography.css","annotation":"other"},{"name":"--ev-w-bold","value":"700","kind":"other","definedIn":"tokens/typography.css","annotation":"other"},{"name":"--ev-w-extrabold","value":"800","kind":"other","definedIn":"tokens/typography.css","annotation":"other"},{"name":"--ev-text-display","value":"40px","kind":"font","definedIn":"tokens/typography.css"},{"name":"--ev-text-h1","value":"28px","kind":"font","definedIn":"tokens/typography.css"},{"name":"--ev-text-h2","value":"22px","kind":"font","definedIn":"tokens/typography.css"},{"name":"--ev-text-h3","value":"18px","kind":"font","definedIn":"tokens/typography.css"},{"name":"--ev-text-h4","value":"16px","kind":"font","definedIn":"tokens/typography.css"},{"name":"--ev-text-lg","value":"15px","kind":"font","definedIn":"tokens/typography.css"},{"name":"--ev-text-base","value":"14px","kind":"font","definedIn":"tokens/typography.css"},{"name":"--ev-text-sm","value":"13px","kind":"font","definedIn":"tokens/typography.css"},{"name":"--ev-text-xs","value":"12px","kind":"font","definedIn":"tokens/typography.css"},{"name":"--ev-text-2xs","value":"11px","kind":"font","definedIn":"tokens/typography.css"},{"name":"--ev-leading-tight","value":"1.15","kind":"font","definedIn":"tokens/typography.css"},{"name":"--ev-leading-snug","value":"1.35","kind":"font","definedIn":"tokens/typography.css"},{"name":"--ev-leading-normal","value":"1.5","kind":"font","definedIn":"tokens/typography.css"},{"name":"--ev-leading-relaxed","value":"1.6","kind":"font","definedIn":"tokens/typography.css"},{"name":"--ev-tracking-tight","value":"-0.02em","kind":"font","definedIn":"tokens/typography.css"},{"name":"--ev-tracking-normal","value":"0","kind":"font","definedIn":"tokens/typography.css"},{"name":"--ev-tracking-label","value":"0.06em","kind":"font","definedIn":"tokens/typography.css"},{"name":"--font-ui","value":"var(--ev-font-sans)","kind":"font","definedIn":"tokens/typography.css"},{"name":"--font-accent","value":"var(--ev-font-sans)","kind":"font","definedIn":"tokens/typography.css"},{"name":"--ev-space-1","value":"4px","kind":"spacing","definedIn":"tokens/spacing.css"},{"name":"--ev-space-2","value":"8px","kind":"spacing","definedIn":"tokens/spacing.css"},{"name":"--ev-space-3","value":"12px","kind":"spacing","definedIn":"tokens/spacing.css"},{"name":"--ev-space-4","value":"16px","kind":"spacing","definedIn":"tokens/spacing.css"},{"name":"--ev-space-5","value":"20px","kind":"spacing","definedIn":"tokens/spacing.css"},{"name":"--ev-space-6","value":"24px","kind":"spacing","definedIn":"tokens/spacing.css"},{"name":"--ev-space-7","value":"28px","kind":"spacing","definedIn":"tokens/spacing.css"},{"name":"--ev-space-8","value":"32px","kind":"spacing","definedIn":"tokens/spacing.css"},{"name":"--ev-space-10","value":"40px","kind":"spacing","definedIn":"tokens/spacing.css"},{"name":"--ev-space-12","value":"48px","kind":"spacing","definedIn":"tokens/spacing.css"},{"name":"--ev-pad-card","value":"18px","kind":"spacing","definedIn":"tokens/spacing.css"},{"name":"--ev-pad-card-lg","value":"24px","kind":"spacing","definedIn":"tokens/spacing.css"},{"name":"--ev-gap-grid","value":"16px","kind":"spacing","definedIn":"tokens/spacing.css"},{"name":"--ev-r-xs","value":"7px","kind":"spacing","definedIn":"tokens/spacing.css"},{"name":"--ev-r-sm","value":"10px","kind":"spacing","definedIn":"tokens/spacing.css"},{"name":"--ev-r-md","value":"12px","kind":"spacing","definedIn":"tokens/spacing.css"},{"name":"--ev-r-lg","value":"18px","kind":"spacing","definedIn":"tokens/spacing.css"},{"name":"--ev-r-xl","value":"24px","kind":"spacing","definedIn":"tokens/spacing.css"},{"name":"--ev-r-2xl","value":"28px","kind":"spacing","definedIn":"tokens/spacing.css"},{"name":"--ev-r-pill","value":"999px","kind":"spacing","definedIn":"tokens/spacing.css"},{"name":"--ev-shadow-xs","value":"0 1px 2px rgba(0,0,0,.05)","kind":"shadow","definedIn":"tokens/spacing.css"},{"name":"--ev-shadow-sm","value":"0 1px 2px rgba(0,0,0,.06)","kind":"shadow","definedIn":"tokens/spacing.css"},{"name":"--ev-shadow-card","value":"0 1px 2px rgba(0,0,0,.04), 0 12px 32px rgba(0,0,0,.05)","kind":"shadow","definedIn":"tokens/spacing.css"},{"name":"--ev-shadow-raised","value":"0 1px 2px rgba(0,0,0,.05), 0 16px 44px rgba(0,0,0,.07)","kind":"shadow","definedIn":"tokens/spacing.css"},{"name":"--ev-shadow-pop","value":"0 10px 34px rgba(0,0,0,.14)","kind":"shadow","definedIn":"tokens/spacing.css"},{"name":"--ev-shadow-chip","value":"0 1px 2px rgba(0,0,0,.06)","kind":"shadow","definedIn":"tokens/spacing.css"},{"name":"--radius-card","value":"var(--ev-r-lg)","kind":"radius","definedIn":"tokens/spacing.css"},{"name":"--radius-button","value":"var(--ev-r-md)","kind":"radius","definedIn":"tokens/spacing.css"},{"name":"--radius-input","value":"var(--ev-r-sm)","kind":"radius","definedIn":"tokens/spacing.css"},{"name":"--shadow-card","value":"var(--ev-shadow-card)","kind":"shadow","definedIn":"tokens/spacing.css"}],"themes":[],"fonts":[],"brandFonts":[{"family":"Fustat","status":"ok","tokens":["--ev-font-sans"],"path":"tokens/typography.css"}],"source":"spa"}